flareec/__init__.py
flareec/dotedrunes/__init__.py
flareec/dotedrunes/flare_encoder.py
flareec-0.1.dist-info/METADATA
flareec-0.1.dist-info/WHEEL
flareec-0.1.dist-info/top_level.txt
flareec-0.1.dist-info/RECORD
