Metadata-Version: 2.1
Name: flareec
Version: 0.1
Summary: A package for with a coding toolset thet kikostudios use an is made to code faster
Home-page: https://github.com/yourusername/flareec
Author: Kiko.Studios
Author-email: hrdykrystof@gmail.com
Classifier: Programming Language :: Python :: 3
Classifier: License :: OSI Approved :: MIT License
Classifier: Operating System :: OS Independent
Requires-Python: >=3.6
